{
  "title": "Cyber Shield Academy: Terminal Ops",
  "slug": "cyber-shield-academy-terminal",
  "entry": "index.html",
  "thumbnail": "thumb.png",
  "orientation": "landscape",
  "category": "Educational",
  "description": "A safe, simulated terminal-based cybersecurity game where players learn UNIX-like commands, defensive investigation, evidence handling, integrity checks, incident response and ethical hacking principles while solving Case BIT.",
  "tags": [
    "cybersecurity",
    "terminal",
    "unix",
    "ethical hacking",
    "education",
    "simulation",
    "puzzle",
    "incident response"
  ],
  "controls": [
    {
      "key": "Keyboard",
      "action": "Type commands in the terminal"
    },
    {
      "key": "Tab",
      "action": "Auto-complete commands, hosts, files and tools"
    },
    {
      "key": "Arrow Up / Down",
      "action": "Command history"
    }
  ],
  "features": {
    "mobileFirst": true,
    "terminalInterface": true,
    "simulatedOnly": true,
    "levels": 8,
    "networkMap": true,
    "fileSystem": true,
    "autoComplete": true,
    "backgroundMusic": true,
    "webAudioSoundEffects": true,
    "scoreBridge": [
      "GG_SCORE",
      "gg:score"
    ],
    "cyberPrinciples": [
      "authorization and scope",
      "least privilege",
      "log preservation",
      "integrity verification",
      "incident response",
      "change management",
      "evidence reporting"
    ]
  },
  "version": "3.0.0-terminal-rebuild"
}